skeem/__init__.py
skeem/autopk.py
skeem/cli.py
skeem/core.py
skeem/exception.py
skeem/io.py
skeem/model.py
skeem/report.py
skeem/settings.py
skeem/type.py
skeem/ddlgen/__init__.py
skeem/ddlgen/ddlgenerator.py
skeem/ddlgen/monkey.py
skeem/ddlgen/reshape.py
skeem/ddlgen/sources.py
skeem/ddlgen/typehelpers.py
skeem/fastparquet/__init__.py
skeem/fastparquet/core.py
skeem/fastparquet/monkey.py
skeem/frictionless/__init__.py
skeem/frictionless/loader_s3.py
skeem/frictionless/loader_stream.py
skeem/frictionless/monkey.py
skeem/frictionless/pandas_plugin.py
skeem/frictionless/parser_jsonl.py
skeem/frictionless/resource.py
skeem/pandas/__init__.py
skeem/pandas/compat.py
skeem/pandas/io_common.py
skeem/pandas/monkey.py
skeem/util/__init__.py
skeem/util/cli.py
skeem/util/data.py
skeem/util/platform.py
skeem/util/report.py
skeem/util/sql.py
skeem-0.1.1.dist-info/LICENSE
skeem-0.1.1.dist-info/METADATA
skeem-0.1.1.dist-info/WHEEL
skeem-0.1.1.dist-info/entry_points.txt
skeem-0.1.1.dist-info/top_level.txt
skeem-0.1.1.dist-info/RECORD
