Metadata-Version: 2.1
Name: skeem
Version: 0.1.1
Summary: Infer SQL DDL statements from tabular data
Author-email: Andreas Motl <andreas.motl@panodata.org>, Benjamin Gutzmann <gutzemann@gmail.com>, Richard Pobering <richard.pobering@panodata.org>
License: MIT
Project-URL: changelog, https://github.com/daq-tools/skeem/blob/main/CHANGES.rst
Project-URL: documentation, https://github.com/daq-tools/skeem
Project-URL: homepage, https://github.com/daq-tools/skeem
Project-URL: repository, https://github.com/daq-tools/skeem
Keywords: csv,ddl,excel,frictionless,gcs,github,grib,gsheet,http,infer,inference,influxdb,introspection,json,jsonl,ldjson,netcdf,ndjson,pandas,parquet,rdbms,reflection,s3,schema,schema conversion,schema inference,spreadsheet,sql,sql-schema,tabular-data
Classifier: Development Status :: 4 - Beta
Classifier: Environment :: Console
Classifier: Intended Audience :: Customer Service
Classifier: Intended Audience :: Developers
Classifier: Intended Audience :: Education
Classifier: Intended Audience :: End Users/Desktop
Classifier: Intended Audience :: Financial and Insurance Industry
Classifier: Intended Audience :: Healthcare Industry
Classifier: Intended Audience :: Information Technology
Classifier: Intended Audience :: Legal Industry
Classifier: Intended Audience :: Manufacturing
Classifier: Intended Audience :: Science/Research
Classifier: Intended Audience :: System Administrators
Classifier: Intended Audience :: Telecommunications Industry
Classifier: License :: OSI Approved :: MIT License
Classifier: Operating System :: MacOS :: MacOS X
Classifier: Operating System :: Microsoft :: Windows
Classifier: Operating System :: POSIX :: Linux
Classifier: Operating System :: Unix
Classifier: Programming Language :: Python
Classifier: Programming Language :: Python :: 3 :: Only
Classifier: Programming Language :: Python :: 3.8
Classifier: Programming Language :: Python :: 3.9
Classifier: Programming Language :: Python :: 3.10
Classifier: Programming Language :: Python :: 3.11
Classifier: Programming Language :: Python :: 3.12
Classifier: Programming Language :: Python :: 3.13
Classifier: Topic :: Communications
Classifier: Topic :: Database
Classifier: Topic :: Documentation
Classifier: Topic :: Education
Classifier: Topic :: Office/Business
Classifier: Topic :: Scientific/Engineering
Classifier: Topic :: Software Development :: Code Generators
Classifier: Topic :: Software Development :: Interpreters
Classifier: Topic :: Software Development :: Libraries
Classifier: Topic :: Software Development :: Testing
Classifier: Topic :: Software Development :: Version Control
Classifier: Topic :: System :: Archiving
Classifier: Topic :: System :: Systems Administration
Classifier: Topic :: Text Processing
Classifier: Topic :: Utilities
Requires-Python: >=3.8
License-File: LICENSE
Requires-Dist: click <9
Requires-Dist: colorama <1
Requires-Dist: crash
Requires-Dist: ddlgenerator <0.2
Requires-Dist: frictionless[excel,json,ods,parquet,sql] <5.19,>=5.16
Requires-Dist: fsspec[gcs,github,http,s3] ==2024.10.0
Requires-Dist: json-stream <3
Requires-Dist: line-protocol-parser <2
Requires-Dist: numpy <3
Requires-Dist: odfpy <2
Requires-Dist: pandas <2.3
Requires-Dist: requests <2.33
Requires-Dist: sql-formatter <0.7
Requires-Dist: sqlalchemy-cratedb ==0.40.0
Requires-Dist: sqlmakeuper <0.2
Requires-Dist: urllib3 <3
Provides-Extra: develop
Requires-Dist: hunter <4 ; extra == 'develop'
Requires-Dist: mypy <1.13 ; extra == 'develop'
Requires-Dist: poethepoet <0.30 ; extra == 'develop'
Requires-Dist: pyproject-fmt <2.5 ; extra == 'develop'
Requires-Dist: ruff <0.8 ; extra == 'develop'
Requires-Dist: types-requests <2.33 ; extra == 'develop'
Requires-Dist: validate-pyproject <0.22 ; extra == 'develop'
Provides-Extra: release
Requires-Dist: build <2 ; extra == 'release'
Requires-Dist: twine <6 ; extra == 'release'
Provides-Extra: scientific
Requires-Dist: cfgrib <1 ; extra == 'scientific'
Requires-Dist: cftime <2 ; extra == 'scientific'
Requires-Dist: scipy <2 ; extra == 'scientific'
Requires-Dist: xarray <2025 ; extra == 'scientific'
Provides-Extra: test
Requires-Dist: pytest <9 ; extra == 'test'
Requires-Dist: pytest-cov <6 ; extra == 'test'
Requires-Dist: pytest-timeout <3 ; extra == 'test'
